<?xml version="1.0" encoding="utf-8" ?>
<plugins>
  <plugin file="CadKit.Plugins.Windows.Properties.plug" load="true" />
  <plugin file="CadKit.Plugins.Windows.OutputWindow.plug" load="true" />
  <plugin file="CadKit.Plugins.Windows.JobWindow.plug" load="true" />
  <plugin file="CadKit.Plugins.Windows.ColorEditor.plug" load="true" />
  <plugin file="CadKit.Plugins.Windows.SnapShot.plug" load="true" />
  <plugin file="DT.Minerva.Plugins.DataExplorer.plug" load="true" />
  <plugin file="DT.Minerva.Plugins.Animate.plug" load="true" />
  <plugin file="DT.Minerva.Plugins.LayerManager.plug" load="true" />
  <plugin file="DT.Minerva.Plugins.Document.plug" load="true" />
</plugins>
